lektorlib-1.2.1.dist-info/METADATA
lektorlib-1.2.1.dist-info/WHEEL
lektorlib-1.2.1.dist-info/licenses/LICENSE
lektorlib/__init__.py
lektorlib/context.py
lektorlib/py.typed
lektorlib/query.py
lektorlib/recordcache.py
lektorlib/testing.py
lektorlib-1.2.1.dist-info/RECORD
