Metadata-Version: 2.1
Name: lektorlib
Version: 1.2.1
Summary: A few bits which are potentially useful to developers of Lektor plugins
Keywords: Lektor utilities
Author-Email: Jeff Dairiki <dairiki@dairiki.org>
License: Copyright © 2020 Geoffrey T. Dairiki
Classifier: Development Status :: 5 - Production/Stable
Classifier: Intended Audience :: Developers
Classifier: License :: OSI Approved :: BSD License
Classifier: Natural Language :: English
Classifier: Programming Language :: Python :: 3
Classifier: Programming Language :: Python :: 3.7
Classifier: Programming Language :: Python :: 3.8
Classifier: Programming Language :: Python :: 3.9
Classifier: Programming Language :: Python :: 3.10
Classifier: Programming Language :: Python :: 3.11
Classifier: Framework :: Lektor
Classifier: Environment :: Plugins
Classifier: Topic :: Software Development :: Libraries
Project-URL: Home, https://github.com/dairiki/lektorlib
Requires-Python: >=3.7
